pretalx_downstream/__init__.py
pretalx_downstream/apps.py
pretalx_downstream/forms.py
pretalx_downstream/models.py
pretalx_downstream/signals.py
pretalx_downstream/tasks.py
pretalx_downstream/urls.py
pretalx_downstream/views.py
pretalx_downstream/locale/django.pot
pretalx_downstream/locale/ar/LC_MESSAGES/django.mo
pretalx_downstream/locale/ar/LC_MESSAGES/django.po
pretalx_downstream/locale/bg/LC_MESSAGES/django.mo
pretalx_downstream/locale/bg/LC_MESSAGES/django.po
pretalx_downstream/locale/ca/LC_MESSAGES/django.mo
pretalx_downstream/locale/ca/LC_MESSAGES/django.po
pretalx_downstream/locale/cs/LC_MESSAGES/django.mo
pretalx_downstream/locale/cs/LC_MESSAGES/django.po
pretalx_downstream/locale/de_DE/LC_MESSAGES/django.mo
pretalx_downstream/locale/de_DE/LC_MESSAGES/django.po
pretalx_downstream/locale/de_Formal/LC_MESSAGES/django.mo
pretalx_downstream/locale/de_Formal/LC_MESSAGES/django.po
pretalx_downstream/locale/el/LC_MESSAGES/django.mo
pretalx_downstream/locale/el/LC_MESSAGES/django.po
pretalx_downstream/locale/en_Mozilla/LC_MESSAGES/django.mo
pretalx_downstream/locale/en_Mozilla/LC_MESSAGES/django.po
pretalx_downstream/locale/es/LC_MESSAGES/django.mo
pretalx_downstream/locale/es/LC_MESSAGES/django.po
pretalx_downstream/locale/es_MX/LC_MESSAGES/django.mo
pretalx_downstream/locale/es_MX/LC_MESSAGES/django.po
pretalx_downstream/locale/fr_FR/LC_MESSAGES/django.mo
pretalx_downstream/locale/fr_FR/LC_MESSAGES/django.po
pretalx_downstream/locale/id/LC_MESSAGES/django.mo
pretalx_downstream/locale/id/LC_MESSAGES/django.po
pretalx_downstream/locale/it/LC_MESSAGES/django.mo
pretalx_downstream/locale/it/LC_MESSAGES/django.po
pretalx_downstream/locale/ja_JP/LC_MESSAGES/django.mo
pretalx_downstream/locale/ja_JP/LC_MESSAGES/django.po
pretalx_downstream/locale/ko/LC_MESSAGES/django.mo
pretalx_downstream/locale/ko/LC_MESSAGES/django.po
pretalx_downstream/locale/nl/LC_MESSAGES/django.mo
pretalx_downstream/locale/nl/LC_MESSAGES/django.po
pretalx_downstream-1.4.0.dist-info/licenses/LICENSE
pretalx_downstream-1.4.0.dist-info/METADATA
pretalx_downstream-1.4.0.dist-info/WHEEL
pretalx_downstream-1.4.0.dist-info/entry_points.txt
pretalx_downstream-1.4.0.dist-info/top_level.txt
pretalx_downstream-1.4.0.dist-info/RECORD
