Metadata-Version: 2.4
Name: pretalx-downstream
Version: 1.4.0
Summary: Use pretalx passively by importing another event's schedule.
Author-email: Tobias Kunze <r@rixx.de>
Maintainer-email: Tobias Kunze <r@rixx.de>
License: Apache Software License
Project-URL: homepage, https://github.com/pretalx/pretalx-downstream
Project-URL: repository, https://github.com/pretalx/pretalx-downstream.git
Keywords: pretalx
License-File: LICENSE
Dynamic: license-file
